{
  "decor": {
    "type": "generic",
    "width": 1.0,
    "height": 0.5,
    "depth": 1.0
  },
  "definitions": [
    {
      "subName": "",
      "modelName": "metal_pile",
      "name": "Metal sheets - tool rack back panel",
      "extraMaterialLists": [
        []
      ]
    }
  ],
  "rendering": {
    "lightObjects": [],
    "modelType": "obj"
  },
  "general": {
    "name": "Metal sheets - tool rack back panel",
    "stackSize": 32,
    "materialLists": [
      ["minecraft:iron_block:0:1"]
    ]
  }
}