{
  "generic": {
    "type": "seat",
    "forwardsDamageMultiplier": 0.0
  },
  "seat": {},
  "parts": [
    {
      "pos": [
        0.0,
        -0.0,
        -0.1875
      ],
      "maxValue": 1.0,
      "types": [
        "generic_npc"
      ],
      "interactableVariables": [
        [
          "!seat_occupied"
        ],
        [
          "!slot_luggage_blocked"
        ],
        [
          "!part_present_2"
        ]
      ],
      "rot": [
        0.0,
        0.0,
        0.0
      ]
    },
    {
      "pos": [
        0.0,
        -0.03125,
        0.0
      ],
      "maxValue": 27.0,
      "types": [
        "interactable_luggage"
      ],
      "interactableVariables": [
        [
          "!seat_occupied"
        ],
        [
          "!slot_luggage_blocked"
        ],
        [
          "!part_present_1"
        ]
      ],
      "rot": [
        -0.0,
        90.0,
        7.0
      ]
    }
  ],
  "definitions": [
    {
      "subName": "_gray",
      "modelName": "trin_seat_1",
      "name": "Model 1 Trin Seat, Gray",
      "extraMaterialLists": [
        [
          "mts:iv_tpp.upholstery_pile_gray:0:1"
        ]
      ]
    },
    {
      "subName": "_white",
      "modelName": "trin_seat_1",
      "name": "Model 1 Trin Seat, White",
      "extraMaterialLists": [
        [
          "mts:iv_tpp.upholstery_pile_white:0:1"
        ]
      ]
    },
    {
      "subName": "_red",
      "modelName": "trin_seat_1",
      "name": "Model 1 Trin Seat, Red",
      "extraMaterialLists": [
        [
          "mts:iv_tpp.upholstery_pile_red:0:1"
        ]
      ]
    },
    {
      "subName": "_beige",
      "modelName": "trin_seat_1",
      "name": "Model 1 Trin Seat, Tan",
      "extraMaterialLists": [
        [
          "mts:iv_tpp.upholstery_pile_beige:0:1"
        ]
      ]
    },
    {
      "subName": "_brown",
      "modelName": "trin_seat_1",
      "name": "Model 1 Trin Seat, Brown",
      "extraMaterialLists": [
        [
          "mts:iv_tpp.upholstery_pile_brown:0:1"
        ]
      ]
    },
    {
      "subName": "_black",
      "modelName": "trin_seat_1",
      "name": "Model 1 Trin Seat, Black",
      "extraMaterialLists": [
        [
          "mts:iv_tpp.upholstery_pile_black:0:1"
        ]
      ]
    },
    {
      "subName": "_junk",
      "modelName": "trin_seat_1",
      "name": "Model 1 Trin Seat, Junk",
      "extraMaterialLists": [
        [
          "mts:iv_tpp.upholstery_pile_gray:0:1",
          "minecraft:dirt:0:1"
        ]
      ]
    },
    {
      "subName": "_grayblue",
      "modelName": "trin_seat_1",
      "name": "Model 1 Trin Seat, Gray And Blue",
      "extraMaterialLists": [
        [
          "mts:iv_tpp.upholstery_pile_grayblue:0:1"
        ]
      ]
    }
  ],
  "rendering": {
    "lightObjects": [],
    "particles": [],
    "modelType": "obj"
  },
  "general": {
    "stackSize": 64,
    "health": 100,
    "materialLists": [
      [
        "minecraft:iron_ingot:0:2",
        "minecraft:string:0:3",
        "minecraft:wool:0:2"
      ]
    ],
    "radarWidth": 0.0,
    "radarRange": 0.0
  }
}